hybridrag/__init__.py
hybridrag/api/__init__.py
hybridrag/api/main.py
hybridrag/api/models.py
hybridrag/config/__init__.py
hybridrag/config/settings.py
hybridrag/core/__init__.py
hybridrag/core/rag.py
hybridrag/engine/__init__.py
hybridrag/engine/base.py
hybridrag/engine/constants.py
hybridrag/engine/exceptions.py
hybridrag/engine/lightrag.py
hybridrag/engine/namespace.py
hybridrag/engine/operate.py
hybridrag/engine/prompt.py
hybridrag/engine/rerank.py
hybridrag/engine/types.py
hybridrag/engine/utils.py
hybridrag/engine/utils_graph.py
hybridrag/engine/api/__init__.py
hybridrag/engine/api/auth.py
hybridrag/engine/api/config.py
hybridrag/engine/api/gunicorn_config.py
hybridrag/engine/api/lightrag_server.py
hybridrag/engine/api/run_with_gunicorn.py
hybridrag/engine/api/utils_api.py
hybridrag/engine/api/routers/__init__.py
hybridrag/engine/api/routers/document_routes.py
hybridrag/engine/api/routers/graph_routes.py
hybridrag/engine/api/routers/ollama_api.py
hybridrag/engine/api/routers/query_routes.py
hybridrag/engine/evaluation/__init__.py
hybridrag/engine/evaluation/eval_rag_quality.py
hybridrag/engine/kg/__init__.py
hybridrag/engine/kg/json_doc_status_impl.py
hybridrag/engine/kg/json_kv_impl.py
hybridrag/engine/kg/mongo_impl.py
hybridrag/engine/kg/shared_storage.py
hybridrag/engine/kg/deprecated/chroma_impl.py
hybridrag/engine/llm/__init__.py
hybridrag/engine/llm/anthropic.py
hybridrag/engine/llm/azure_openai.py
hybridrag/engine/llm/bedrock.py
hybridrag/engine/llm/binding_options.py
hybridrag/engine/llm/gemini.py
hybridrag/engine/llm/hf.py
hybridrag/engine/llm/jina.py
hybridrag/engine/llm/llama_index_impl.py
hybridrag/engine/llm/lmdeploy.py
hybridrag/engine/llm/lollms.py
hybridrag/engine/llm/nvidia_openai.py
hybridrag/engine/llm/ollama.py
hybridrag/engine/llm/openai.py
hybridrag/engine/llm/zhipu.py
hybridrag/engine/llm/deprecated/siliconcloud.py
hybridrag/engine/tools/__init__.py
hybridrag/engine/tools/check_initialization.py
mongodb_hybridrag-0.3.0.dist-info/licenses/LICENSE
mongodb_hybridrag-0.3.0.dist-info/METADATA
mongodb_hybridrag-0.3.0.dist-info/WHEEL
mongodb_hybridrag-0.3.0.dist-info/top_level.txt
mongodb_hybridrag-0.3.0.dist-info/RECORD
