Metadata-Version: 2.4
Name: mongodb-hybridrag
Version: 0.3.0
Summary: State-of-the-art RAG system with MongoDB Atlas and Voyage AI
Author-email: MongoDB <devrel@mongodb.com>
License: Apache-2.0
Project-URL: Homepage, https://github.com/romiluz13/Hybrid-Search-RAG
Project-URL: Documentation, https://github.com/romiluz13/Hybrid-Search-RAG#readme
Project-URL: Repository, https://github.com/romiluz13/Hybrid-Search-RAG
Project-URL: Issues, https://github.com/romiluz13/Hybrid-Search-RAG/issues
Keywords: rag,retrieval-augmented-generation,mongodb,atlas,vector-search,voyage-ai,knowledge-graph,llm,ai
Classifier: Development Status :: 4 - Beta
Classifier: Intended Audience :: Developers
Classifier: License :: OSI Approved :: Apache Software License
Classifier: Operating System :: OS Independent
Classifier: Programming Language :: Python :: 3
Classifier: Programming Language :: Python :: 3.11
Classifier: Programming Language :: Python :: 3.12
Classifier: Topic :: Scientific/Engineering :: Artificial Intelligence
Classifier: Topic :: Database
Classifier: Typing :: Typed
Requires-Python: >=3.11
License-File: LICENSE
Requires-Dist: numpy>=1.24.0
Requires-Dist: python-dotenv>=1.0.0
Requires-Dist: pydantic>=2.0.0
Requires-Dist: pydantic-settings>=2.0.0
Requires-Dist: voyageai>=0.3.0
Requires-Dist: anthropic>=0.39.0
Requires-Dist: openai>=1.0.0
Requires-Dist: google-generativeai>=0.8.0
Requires-Dist: pymongo>=4.6.0
Requires-Dist: motor>=3.3.0
Requires-Dist: tiktoken>=0.8.0
Requires-Dist: tenacity>=9.0.0
Requires-Dist: aioboto3>=13.2.0
Requires-Dist: aiohttp>=3.11.9
Provides-Extra: api
Requires-Dist: fastapi>=0.109.0; extra == "api"
Requires-Dist: uvicorn>=0.27.0; extra == "api"
Provides-Extra: ui
Requires-Dist: chainlit>=1.0.0; extra == "ui"
Requires-Dist: pymupdf>=1.23.0; extra == "ui"
Provides-Extra: observability
Requires-Dist: langfuse>=2.0.0; extra == "observability"
Provides-Extra: evaluation
Requires-Dist: ragas>=0.2.0; extra == "evaluation"
Requires-Dist: datasets>=2.14.0; extra == "evaluation"
Requires-Dist: langchain-openai>=0.2.0; extra == "evaluation"
Provides-Extra: dev
Requires-Dist: pytest>=7.0.0; extra == "dev"
Requires-Dist: pytest-asyncio>=0.23.0; extra == "dev"
Requires-Dist: pytest-cov>=4.0.0; extra == "dev"
Requires-Dist: black>=24.0.0; extra == "dev"
Requires-Dist: isort>=5.13.0; extra == "dev"
Requires-Dist: mypy>=1.8.0; extra == "dev"
Requires-Dist: ruff>=0.2.0; extra == "dev"
Provides-Extra: all
Requires-Dist: mongodb-hybridrag[api,dev,evaluation,observability,ui]; extra == "all"
Dynamic: license-file
